{
  "parent": "immersiveengineering:main/craft_drop_conveyor",
  "criteria": {
    "code_trigger": {
      "trigger": "minecraft:impossible"
    }
  },
  "display": {
    "announce_to_chat": true,
    "description": {
      "translate": "advancement.immersiveengineering.chute_bonk.desc"
    },
    "frame": "task",
    "hidden": false,
    "icon": {
      "item": "immersiveengineering:chute_iron"
    },
    "show_toast": true,
    "title": {
      "translate": "advancement.immersiveengineering.chute_bonk"
    }
  },
  "requirements": [
    [
      "code_trigger"
    ]
  ],
  "sends_telemetry_event": false
}