{
  "type": "immersiveengineering:hammer_crushing",
  "conditions": [
    {
      "key": "tools.disable_hammer_crushing",
      "value": false,
      "type": "immersiveengineering:config"
    },
    {
      "value": {
        "tag": "forge:dusts/ardite",
        "type": "forge:tag_empty"
      },
      "type": "forge:not"
    },
    {
      "value": {
        "tag": "forge:ores/ardite",
        "type": "forge:tag_empty"
      },
      "type": "forge:not"
    }
  ],
  "result": {
    "tag": "forge:dusts/ardite"
  },
  "input": {
    "tag": "forge:ores/ardite"
  }
}