{
  "parent": "minecraft:recipes/root",
  "criteria": {
    "has_dust_constantan": {
      "conditions": {
        "items": [
          {
            "items": [
              "immersiveengineering:dust_constantan"
            ]
          }
        ]
      },
      "trigger": "minecraft:inventory_changed"
    },
    "has_the_recipe": {
      "conditions": {
        "recipe": "immersiveengineering:smelting/ingot_constantan_from_dust_from_blasting"
      },
      "trigger": "minecraft:recipe_unlocked"
    }
  },
  "requirements": [
    [
      "has_dust_constantan",
      "has_the_recipe"
    ]
  ],
  "rewards": {
    "recipes": [
      "immersiveengineering:smelting/ingot_constantan_from_dust_from_blasting"
    ]
  },
  "sends_telemetry_event": false
}