{
	"forge_marker": 1,
	"defaults":
	{
		"transform": "forge:default-block",
		"model": "immersiveengineering:ie_slab",
		"textures": {
			"all": "immersiveengineering:blocks/treated_wood_horizontal",
			"bottom": "#all",
			"top": "#all",
			"side": "#all",
			"particle": "#all"
		}
	},
	"variants":
	{
		"inventory,type=horizontal": [{"textures": {"all": "immersiveengineering:blocks/treated_wood_horizontal"}}],
		"inventory,type=vertical": [{"textures": {"all": "immersiveengineering:blocks/treated_wood_vertical"}}],
		"inventory,type=packaged": [{"textures": {"all": "immersiveengineering:blocks/treated_wood_packaged"}}],
		"type":
		{
			"horizontal": {"textures": {"all": "immersiveengineering:blocks/treated_wood_horizontal"}},
			"vertical": {"textures": {"all": "immersiveengineering:blocks/treated_wood_vertical"}},
			"packaged": {"textures": {"all": "immersiveengineering:blocks/treated_wood_packaged"}}
		},
		"slabtype":
		{
          "0": {},
          "1": {
				"x": 180,
				"uvlock": true
			},
          "2": {
				"model": "cube_all"
			}
		}
	}
}