{
  "parent": "immersiveengineering:multiblocks/mb_squeezer",
  "criteria": {
    "form_multiblock": {
      "conditions": {
        "item": {
          "items": [
            "immersiveengineering:hammer"
          ]
        },
        "multiblock": "immersiveengineering:multiblocks/fermenter"
      },
      "trigger": "immersiveengineering:multiblock_formed"
    }
  },
  "display": {
    "announce_to_chat": true,
    "description": {
      "translate": "advancement.immersiveengineering.mb_fermenter.desc"
    },
    "frame": "task",
    "hidden": false,
    "icon": {
      "item": "immersiveengineering:fermenter"
    },
    "show_toast": true,
    "title": {
      "translate": "advancement.immersiveengineering.mb_fermenter"
    }
  },
  "requirements": [
    [
      "form_multiblock"
    ]
  ],
  "sends_telemetry_event": false
}