{
	"display": {
		"icon": {
			"item": "immersiveengineering:skyhook"
		},
		"title": {
			"translate": "advancement.immersiveengineering:craftSkyhook"
		},
		"description": {
			"translate": "advancement.immersiveengineering:craftSkyhook.desc"
		}
	},
	"parent": "immersiveengineering:main/craft_workbench",
	"criteria": {
		"craft_hammer": {
			"trigger": "minecraft:inventory_changed",
			"conditions": {
				"items": [
					{
						"item": "immersiveengineering:skyhook"
					}
				]
			}
		}
	}
}