{
  "parent": "minecraft:recipes/root",
  "rewards": {
    "recipes": [
      "immersiveengineering:crafting/conveyor_splittercovered"
    ]
  },
  "criteria": {
    "has_vertical_conveyor": {
      "trigger": "minecraft:inventory_changed",
      "conditions": {
        "items": [
          {
            "item": "immersiveengineering:conveyor_splitter"
          }
        ]
      }
    },
    "has_the_recipe": {
      "trigger": "minecraft:recipe_unlocked",
      "conditions": {
        "recipe": "immersiveengineering:crafting/conveyor_splittercovered"
      }
    }
  },
  "requirements": [
    [
      "has_vertical_conveyor",
      "has_the_recipe"
    ]
  ]
}