{
  "parent": "immersiveengineering:tools/craft_railgun",
  "criteria": {
    "code_trigger": {
      "trigger": "minecraft:impossible"
    }
  },
  "display": {
    "description": {
      "translate": "advancement.immersiveengineering.upgrade_railgun.desc"
    },
    "frame": "challenge",
    "icon": {
      "item": "immersiveengineering:railgun",
      "nbt": "{upgrades:{scope:1b,speed:1.0f}}"
    },
    "title": {
      "translate": "advancement.immersiveengineering.upgrade_railgun"
    }
  },
  "requirements": [
    [
      "code_trigger"
    ]
  ],
  "rewards": {
    "loot": [
      "immersiveengineering:advancements/shader_rare"
    ]
  }
}