{
  "parent": "minecraft:recipes/root",
  "rewards": {
    "recipes": [
      "immersiveengineering:smelting/ingot_nickel2"
    ]
  },
  "criteria": {
    "has_deepslate_ore_nickel": {
      "trigger": "minecraft:inventory_changed",
      "conditions": {
        "items": [
          {
            "items": [
              "immersiveengineering:deepslate_ore_nickel"
            ]
          }
        ]
      }
    },
    "has_the_recipe": {
      "trigger": "minecraft:recipe_unlocked",
      "conditions": {
        "recipe": "immersiveengineering:smelting/ingot_nickel2"
      }
    }
  },
  "requirements": [
    [
      "has_deepslate_ore_nickel",
      "has_the_recipe"
    ]
  ]
}